firefly_cli/__init__.py
firefly_cli/__main__.py
firefly_cli/_version.py
firefly_cli/api.py
firefly_cli/bcolors.py
firefly_cli/cli.py
firefly_cli/configs.py
firefly_cli/logger.py
firefly_cli/parser.py
firefly_cli/transaction.py
firefly_cli/utils.py
test/__init__.py
test/conftest.py
test/test_api.py
test/test_cli.py
test/test_configs.py
test/test_parser.py
test/test_transaction.py
test/test_utils.py
test/utils.py
firefly_cli-0.2.2.dist-info/METADATA
firefly_cli-0.2.2.dist-info/WHEEL
firefly_cli-0.2.2.dist-info/entry_points.txt
firefly_cli-0.2.2.dist-info/top_level.txt
firefly_cli-0.2.2.dist-info/RECORD
