Metadata-Version: 2.1
Name: firefly-cli
Version: 0.2.2
Summary: A python-based command line interface for practically entering expenses in Firefly III
Home-page: https://github.com/afonsoc12/firefly-cli
Author: Afonso Costa
License: Apache-2.0 license
Classifier: Development Status :: 3 - Alpha
Classifier: Programming Language :: Python :: 3
Classifier: License :: OSI Approved :: Apache Software License
Classifier: Operating System :: OS Independent
Requires-Dist: cmd2 <3,>=2.4.1
Requires-Dist: requests-cache <1,>=0.9.4
Requires-Dist: tabulate <1,>=0.8.9
Requires-Dist: pyxdg <1,>=0.28
